ohlc2/__init__.py
ohlc2-0.1.0.dist-info/DESCRIPTION.rst
ohlc2-0.1.0.dist-info/METADATA
ohlc2-0.1.0.dist-info/RECORD
ohlc2-0.1.0.dist-info/WHEEL
ohlc2-0.1.0.dist-info/metadata.json
ohlc2-0.1.0.dist-info/top_level.txt
tests/__init__.py
tests/test_sample.py
